fishertools/__init__.py
fishertools/_version.py
fishertools/decorators.py
fishertools/helpers.py
fishertools/input_utils.py
fishertools/integration.py
fishertools/readme_transformer.py
fishertools/transform_readme.py
fishertools/utils.py
fishertools/config/__init__.py
fishertools/config/manager.py
fishertools/config/models.py
fishertools/config/parser.py
fishertools/debug/__init__.py
fishertools/debug/debugger.py
fishertools/debug/tracer.py
fishertools/documentation/__init__.py
fishertools/documentation/api.py
fishertools/documentation/code_validator.py
fishertools/documentation/examples_manager.py
fishertools/documentation/generator.py
fishertools/documentation/managers.py
fishertools/documentation/models.py
fishertools/documentation/visual.py
fishertools/errors/__init__.py
fishertools/errors/exception_types.py
fishertools/errors/exceptions.py
fishertools/errors/explainer.py
fishertools/errors/explanation_builder.py
fishertools/errors/formatters.py
fishertools/errors/models.py
fishertools/errors/pattern_loader.py
fishertools/errors/patterns.py
fishertools/errors/recovery.py
fishertools/examples/__init__.py
fishertools/examples/cli_example.py
fishertools/examples/debug_examples.py
fishertools/examples/learn_example.py
fishertools/examples/logger_example.py
fishertools/examples/menu_example.py
fishertools/examples/models.py
fishertools/examples/repository.py
fishertools/examples/storage_example.py
fishertools/examples/validation_examples.py
fishertools/examples/visualization_examples.py
fishertools/learn/__init__.py
fishertools/learn/examples.py
fishertools/learn/knowledge_engine.py
fishertools/learn/test_knowledge_engine.py
fishertools/learn/test_knowledge_engine_pbt.py
fishertools/learn/tips.py
fishertools/learn/repl/__init__.py
fishertools/learn/repl/cli.py
fishertools/learn/repl/code_sandbox.py
fishertools/learn/repl/command_handler.py
fishertools/learn/repl/command_parser.py
fishertools/learn/repl/engine.py
fishertools/learn/repl/models.py
fishertools-0.4.4.2.dist-info/licenses/LICENSE
fishertools-0.4.4.2.dist-info/METADATA
fishertools-0.4.4.2.dist-info/WHEEL
fishertools-0.4.4.2.dist-info/top_level.txt
fishertools-0.4.4.2.dist-info/RECORD
