Metadata-Version: 2.4
Name: fishertools
Version: 0.4.4.2
Summary: Fishertools - инструменты, которые делают Python удобнее и безопаснее для новичков
Home-page: https://github.com/f1sherFM/My_1st_library_python
Author: f1sherFM
Author-email: f1sherFM <kirillka229top@gmail.com>
License: MIT
Project-URL: Homepage, https://github.com/f1sherFM/My_1st_library_python
Project-URL: Repository, https://github.com/f1sherFM/My_1st_library_python
Project-URL: Issues, https://github.com/f1sherFM/My_1st_library_python/issues
Classifier: Development Status :: 3 - Alpha
Classifier: Intended Audience :: Developers
Classifier: License :: OSI Approved :: MIT License
Classifier: Operating System :: OS Independent
Classifier: Programming Language :: Python :: 3
Classifier: Programming Language :: Python :: 3.8
Classifier: Programming Language :: Python :: 3.9
Classifier: Programming Language :: Python :: 3.10
Classifier: Programming Language :: Python :: 3.11
Classifier: Programming Language :: Python :: 3.12
Classifier: Programming Language :: Python :: 3.13
Classifier: Programming Language :: Python :: 3.14
Requires-Python: >=3.8
License-File: LICENSE
Requires-Dist: requests<3.0.0,>=2.31.0
Requires-Dist: click<9.0.0,>=8.3.0
Provides-Extra: config
Requires-Dist: pyyaml<7.0.0,>=6.0.0; extra == "config"
Provides-Extra: dev
Requires-Dist: pytest<10.0.0,>=9.0.0; extra == "dev"
Requires-Dist: hypothesis<7.0.0,>=6.150.0; extra == "dev"
Requires-Dist: black<25.0.0,>=24.0.0; extra == "dev"
Requires-Dist: ruff<1.0.0,>=0.1.0; extra == "dev"
Requires-Dist: mypy<2.0.0,>=1.8.0; extra == "dev"
Provides-Extra: all
Requires-Dist: fishertools[config]; extra == "all"
Dynamic: author
Dynamic: home-page
Dynamic: license-file
Dynamic: requires-python
